{
    "description": "",
    "tags": [],
    "size": {
        "height": 720,
        "width": 1280
    },
    "objects": [
        {
            "id": 869197024,
            "classId": 9943772,
            "description": "",
            "geometryType": "rectangle",
            "labelerLogin": "Anelliator",
            "createdAt": "2022-01-22T17:24:57.737Z",
            "updatedAt": "2022-01-22T17:24:57.737Z",
            "tags": [],
            "classTitle": "blueball",
            "points": {
                "exterior": [
                    [
                        491,
                        118
                    ],
                    [
                        604,
                        236
                    ]
                ],
                "interior": []
            }
        }
    ]
}