{
    "description": "",
    "tags": [],
    "size": {
        "height": 720,
        "width": 1280
    },
    "objects": [
        {
            "id": 869211706,
            "classId": 9943758,
            "description": "",
            "geometryType": "rectangle",
            "labelerLogin": "thecodewizard",
            "createdAt": "2022-01-22T20:23:55.437Z",
            "updatedAt": "2022-01-22T20:23:55.437Z",
            "tags": [],
            "classTitle": "redball",
            "points": {
                "exterior": [
                    [
                        139,
                        520
                    ],
                    [
                        461,
                        719
                    ]
                ],
                "interior": []
            }
        }
    ]
}