{
    "description": "",
    "tags": [],
    "size": {
        "height": 720,
        "width": 1280
    },
    "objects": [
        {
            "id": 869211285,
            "classId": 9943758,
            "description": "",
            "geometryType": "rectangle",
            "labelerLogin": "thecodewizard",
            "createdAt": "2022-01-22T20:14:01.561Z",
            "updatedAt": "2022-01-22T20:14:01.561Z",
            "tags": [],
            "classTitle": "redball",
            "points": {
                "exterior": [
                    [
                        451,
                        470
                    ],
                    [
                        523,
                        550
                    ]
                ],
                "interior": []
            }
        }
    ]
}