{
    "description": "",
    "tags": [],
    "size": {
        "height": 720,
        "width": 1280
    },
    "objects": [
        {
            "id": 869212313,
            "classId": 9943772,
            "description": "",
            "geometryType": "rectangle",
            "labelerLogin": "Anelliator",
            "createdAt": "2022-01-22T20:43:28.614Z",
            "updatedAt": "2022-01-22T20:43:28.614Z",
            "tags": [],
            "classTitle": "blueball",
            "points": {
                "exterior": [
                    [
                        627,
                        155
                    ],
                    [
                        831,
                        352
                    ]
                ],
                "interior": []
            }
        }
    ]
}