{
    "description": "",
    "tags": [],
    "size": {
        "height": 720,
        "width": 1280
    },
    "objects": [
        {
            "id": 869211287,
            "classId": 9943772,
            "description": "",
            "geometryType": "rectangle",
            "labelerLogin": "firebanner64",
            "createdAt": "2022-01-22T20:14:04.861Z",
            "updatedAt": "2022-01-22T20:14:04.861Z",
            "tags": [],
            "classTitle": "blueball",
            "points": {
                "exterior": [
                    [
                        774,
                        592
                    ],
                    [
                        919,
                        718
                    ]
                ],
                "interior": []
            }
        }
    ]
}